survey_analysis/VERSION
survey_analysis/__init__.py
survey_analysis/config.yml
survey_analysis/pipeline.py
survey_analysis/predict.py
survey_analysis/train_pipeline.py
survey_analysis/config/__init__.py
survey_analysis/config/core.py
survey_analysis/datasets/__init__.py
survey_analysis/processing/__init__.py
survey_analysis/processing/data_manager.py
survey_analysis/processing/features.py
survey_analysis/processing/plotting.py
survey_analysis/processing/utils.py
survey_analysis/processing/validation.py
survey_analysis/trained_models/__init__.py
survey_analysis/trained_models/salary_gb_pipeline_v0.0.1.pkl
tid_salary_survey_prediction-0.0.1.dist-info/LICENSE
tid_salary_survey_prediction-0.0.1.dist-info/METADATA
tid_salary_survey_prediction-0.0.1.dist-info/WHEEL
tid_salary_survey_prediction-0.0.1.dist-info/top_level.txt
tid_salary_survey_prediction-0.0.1.dist-info/RECORD
